livepeer_ai/__init__.py
livepeer_ai/_hooks/__init__.py
livepeer_ai/_hooks/registration.py
livepeer_ai/_hooks/sdkhooks.py
livepeer_ai/_hooks/types.py
livepeer_ai/_version.py
livepeer_ai/basesdk.py
livepeer_ai/generate.py
livepeer_ai/httpclient.py
livepeer_ai/models/components/__init__.py
livepeer_ai/models/components/apierror.py
livepeer_ai/models/components/audioresponse.py
livepeer_ai/models/components/body_genaudiototext.py
livepeer_ai/models/components/body_genimagetoimage.py
livepeer_ai/models/components/body_genimagetotext.py
livepeer_ai/models/components/body_genimagetovideo.py
livepeer_ai/models/components/body_gensegmentanything2.py
livepeer_ai/models/components/body_genupscale.py
livepeer_ai/models/components/chunk.py
livepeer_ai/models/components/httpmetadata.py
livepeer_ai/models/components/imageresponse.py
livepeer_ai/models/components/imagetotextresponse.py
livepeer_ai/models/components/livevideotovideoparams.py
livepeer_ai/models/components/livevideotovideoresponse.py
livepeer_ai/models/components/llmchoice.py
livepeer_ai/models/components/llmmessage.py
livepeer_ai/models/components/llmrequest.py
livepeer_ai/models/components/llmresponse.py
livepeer_ai/models/components/llmtokenusage.py
livepeer_ai/models/components/masksresponse.py
livepeer_ai/models/components/media.py
livepeer_ai/models/components/mediaurl.py
livepeer_ai/models/components/security.py
livepeer_ai/models/components/textresponse.py
livepeer_ai/models/components/texttoimageparams.py
livepeer_ai/models/components/texttospeechparams.py
livepeer_ai/models/components/validationerror.py
livepeer_ai/models/components/videoresponse.py
livepeer_ai/models/errors/__init__.py
livepeer_ai/models/errors/httperror.py
livepeer_ai/models/errors/httpvalidationerror.py
livepeer_ai/models/errors/sdkerror.py
livepeer_ai/models/operations/__init__.py
livepeer_ai/models/operations/genaudiototext.py
livepeer_ai/models/operations/genimagetoimage.py
livepeer_ai/models/operations/genimagetotext.py
livepeer_ai-0.10.0.dist-info/METADATA
livepeer_ai-0.10.0.dist-info/WHEEL
livepeer_ai-0.10.0.dist-info/RECORD
